{"textures":{"0":"modelengine:entity/rhino"},"elements":[{"name":"cube","from":[5.97824,1.0275197,6.2478075],"to":[10.021761,9.11456,10.740608],"rotation":{"angle":0.0,"axis":"x","origin":[13.571073,17.875523,7.8202877]},"faces":{"down":{"uv":[10.75,11.75,10.25,12.375],"rotation":0,"texture":"#0","tintindex":0},"east":{"uv":[10.5,5.5,11.125,6.625],"rotation":0,"texture":"#0","tintindex":0},"north":{"uv":[4.0,7.5,4.5,8.625],"rotation":0,"texture":"#0","tintindex":0},"south":{"uv":[11.25,6.0,11.75,7.125],"rotation":0,"texture":"#0","tintindex":0},"up":{"uv":[9.75,12.375,9.25,11.75],"rotation":0,"texture":"#0","tintindex":0},"west":{"uv":[10.5,6.75,11.125,7.875],"rotation":0,"texture":"#0","tintindex":0}}},{"name":"cube","from":[5.52896,-1.6681604,4.0014076],"to":[10.471041,1.9260801,11.010176],"rotation":{"angle":0.0,"axis":"x","origin":[13.571073,17.875523,7.8202877]},"faces":{"down":{"uv":[11.625,9.0,11.0,10.0],"rotation":0,"texture":"#0","tintindex":0},"east":{"uv":[7.0,4.75,8.0,5.25],"rotation":0,"texture":"#0","tintindex":0},"north":{"uv":[11.75,11.5,12.375,12.0],"rotation":0,"texture":"#0","tintindex":0},"south":{"uv":[12.0,5.0,12.625,5.5],"rotation":0,"texture":"#0","tintindex":0},"up":{"uv":[11.125,9.0,10.5,8.0],"rotation":0,"texture":"#0","tintindex":0},"west":{"uv":[8.5,7.5,9.5,8.0],"rotation":0,"texture":"#0","tintindex":0}}}],"display":{"head":{"translation":[0.0,-6.4,0.0],"rotation":[0.0,0.0,0.0],"scale":[3.8095,3.8095,3.8095]}}}