{"textures":{"0":"modelengine:entity/blackbear"},"elements":[{"name":"cube","from":[5.9839993,3.83,6.0599995],"to":[10.016,8.702,10.092],"rotation":{"angle":0.0,"axis":"x","origin":[11.696,13.574,19.5]},"faces":{"down":{"uv":[9.5,7.625,8.75,8.375],"rotation":0,"texture":"#0","tintindex":0},"east":{"uv":[5.625,8.625,6.375,9.375],"rotation":0,"texture":"#0","tintindex":0},"north":{"uv":[8.625,0.0,9.375,0.75],"rotation":0,"texture":"#0","tintindex":0},"south":{"uv":[6.375,8.625,7.125,9.375],"rotation":0,"texture":"#0","tintindex":0},"up":{"uv":[7.875,9.5,7.125,8.75],"rotation":0,"texture":"#0","tintindex":0},"west":{"uv":[8.75,0.75,9.5,1.5],"rotation":0,"texture":"#0","tintindex":0}}},{"name":"cube","from":[6.3199997,1.8140001,4.38],"to":[9.68,3.158,10.092],"rotation":{"angle":0.0,"axis":"x","origin":[11.696,13.574,19.5]},"faces":{"down":{"uv":[5.0,8.125,4.375,9.1875],"rotation":0,"texture":"#0","tintindex":0},"east":{"uv":[10.0,1.375,11.0625,1.625],"rotation":0,"texture":"#0","tintindex":0},"north":{"uv":[0.875,6.0,1.5,6.25],"rotation":0,"texture":"#0","tintindex":0},"south":{"uv":[6.625,1.125,7.25,1.375],"rotation":0,"texture":"#0","tintindex":0},"up":{"uv":[7.9375,1.8125,7.3125,0.75],"rotation":0,"texture":"#0","tintindex":0},"west":{"uv":[10.0,1.625,11.0625,1.875],"rotation":0,"texture":"#0","tintindex":0}}},{"name":"cube","from":[6.3199997,3.158,6.396],"to":[9.68,3.83,10.092],"rotation":{"angle":0.0,"axis":"x","origin":[11.696,13.574,19.5]},"faces":{"down":{"uv":[10.125,2.25,9.5,2.9375],"rotation":0,"texture":"#0","tintindex":0},"east":{"uv":[5.25,1.375,5.9375,1.5],"rotation":0,"texture":"#0","tintindex":0},"north":{"uv":[0.875,6.25,1.5,6.375],"rotation":0,"texture":"#0","tintindex":0},"south":{"uv":[7.5,1.0,8.125,1.125],"rotation":0,"texture":"#0","tintindex":0},"up":{"uv":[2.25,10.1875,1.625,9.5],"rotation":0,"texture":"#0","tintindex":0},"west":{"uv":[10.125,3.0,10.8125,3.125],"rotation":0,"texture":"#0","tintindex":0}}},{"name":"cube","from":[9.008,1.8140001,3.876],"to":[9.68,2.8220003,4.38],"rotation":{"angle":0.0,"axis":"x","origin":[11.696,12.2300005,19.5]},"faces":{"down":{"uv":[5.625,9.25,5.5,9.375],"rotation":0,"texture":"#0","tintindex":0},"east":{"uv":[7.5,10.25,7.625,10.4375],"rotation":0,"texture":"#0","tintindex":0},"north":{"uv":[7.375,10.25,7.5,10.4375],"rotation":0,"texture":"#0","tintindex":0},"south":{"uv":[10.375,0.875,10.5,1.0625],"rotation":0,"texture":"#0","tintindex":0},"up":{"uv":[9.375,2.625,9.25,2.5],"rotation":0,"texture":"#0","tintindex":0},"west":{"uv":[10.375,1.125,10.5,1.3125],"rotation":0,"texture":"#0","tintindex":0}}},{"name":"cube","from":[7.664,1.8140001,3.876],"to":[8.3359995,2.8220003,4.38],"rotation":{"angle":0.0,"axis":"x","origin":[11.696,12.2300005,19.5]},"faces":{"down":{"uv":[7.125,9.375,7.0,9.5],"rotation":0,"texture":"#0","tintindex":0},"east":{"uv":[10.375,2.375,10.5,2.5625],"rotation":0,"texture":"#0","tintindex":0},"north":{"uv":[10.375,2.125,10.5,2.3125],"rotation":0,"texture":"#0","tintindex":0},"south":{"uv":[3.5,10.375,3.625,10.5625],"rotation":0,"texture":"#0","tintindex":0},"up":{"uv":[9.5,2.625,9.375,2.5],"rotation":0,"texture":"#0","tintindex":0},"west":{"uv":[3.625,10.375,3.75,10.5625],"rotation":0,"texture":"#0","tintindex":0}}},{"name":"cube","from":[6.3199997,1.8140001,3.876],"to":[6.9919996,2.8220003,4.38],"rotation":{"angle":0.0,"axis":"x","origin":[11.696,12.2300005,19.5]},"faces":{"down":{"uv":[2.5,9.75,2.375,9.875],"rotation":0,"texture":"#0","tintindex":0},"east":{"uv":[3.875,10.375,4.0,10.5625],"rotation":0,"texture":"#0","tintindex":0},"north":{"uv":[3.75,10.375,3.875,10.5625],"rotation":0,"texture":"#0","tintindex":0},"south":{"uv":[4.0,10.375,4.125,10.5625],"rotation":0,"texture":"#0","tintindex":0},"up":{"uv":[2.375,9.875,2.25,9.75],"rotation":0,"texture":"#0","tintindex":0},"west":{"uv":[4.125,10.375,4.25,10.5625],"rotation":0,"texture":"#0","tintindex":0}}}],"display":{"head":{"translation":[0.0,-6.4,0.0],"rotation":[0.0,0.0,0.0],"scale":[3.8095,3.8095,3.8095]}}}